os_android_play_console_automation
